mcp_server_analyzer/__init__.py
mcp_server_analyzer/__main__.py
mcp_server_analyzer/models.py
mcp_server_analyzer/server.py
mcp_server_analyzer/analyzers/__init__.py
mcp_server_analyzer/analyzers/ruff.py
mcp_server_analyzer/analyzers/vulture.py
mcp_server_analyzer-0.1.1.dist-info/METADATA
mcp_server_analyzer-0.1.1.dist-info/WHEEL
mcp_server_analyzer-0.1.1.dist-info/entry_points.txt
mcp_server_analyzer-0.1.1.dist-info/licenses/LICENSE
mcp_server_analyzer-0.1.1.dist-info/RECORD
