Metadata-Version: 2.4
Name: mcp-server-analyzer
Version: 0.1.1
Summary: MCP server for Python code analysis with RUFF linting and VULTURE dead code detection
Project-URL: Homepage, https://github.com/anselmoo/mcp-server-analyzer
Project-URL: Documentation, https://github.com/anselmoo/mcp-server-analyzer
Project-URL: Repository, https://github.com/anselmoo/mcp-server-analyzer
Project-URL: Issues, https://github.com/anselmoo/mcp-server-analyzer/issues
Author-email: Anselm Hahn <anselm.hahn@gmail.com>
Maintainer-email: Anselm Hahn <anselm.hahn@gmail.com>
License: MIT
License-File: LICENSE
Keywords: code-analysis,linting,mcp,python,ruff,static-analysis,vulture
Classifier: Development Status :: 4 - Beta
Classifier: Intended Audience :: Developers
Classifier: License :: OSI Approved :: MIT License
Classifier: Programming Language :: Python :: 3
Classifier: Programming Language :: Python :: 3.10
Classifier: Programming Language :: Python :: 3.11
Classifier: Programming Language :: Python :: 3.12
Classifier: Topic :: Software Development :: Libraries :: Python Modules
Classifier: Topic :: Software Development :: Quality Assurance
Requires-Python: >=3.10
Requires-Dist: fastmcp>=0.3.0
Requires-Dist: pydantic>=2.0.0
Requires-Dist: ruff>=0.8.0
Requires-Dist: vulture>=2.11
Provides-Extra: dev
Requires-Dist: bandit>=1.7.0; extra == 'dev'
Requires-Dist: black>=23.0.0; extra == 'dev'
Requires-Dist: mypy>=1.0.0; extra == 'dev'
Requires-Dist: pre-commit>=3.0.0; extra == 'dev'
Requires-Dist: pytest-asyncio>=0.21.0; extra == 'dev'
Requires-Dist: pytest-cov>=4.0.0; extra == 'dev'
Requires-Dist: pytest>=8.4.1; extra == 'dev'
Requires-Dist: safety>=2.0.0; extra == 'dev'
Provides-Extra: test
Requires-Dist: pytest-asyncio>=0.21.0; extra == 'test'
Requires-Dist: pytest-cov>=4.0.0; extra == 'test'
Requires-Dist: pytest>=8.4.1; extra == 'test'
